videodb_director_mcp/__init__.py
videodb_director_mcp/cli_commands.py
videodb_director_mcp/constants.py
videodb_director_mcp/main.py
videodb_director_mcp-0.1.7.dist-info/METADATA
videodb_director_mcp-0.1.7.dist-info/WHEEL
videodb_director_mcp-0.1.7.dist-info/entry_points.txt
videodb_director_mcp-0.1.7.dist-info/top_level.txt
videodb_director_mcp-0.1.7.dist-info/RECORD
