Metadata-Version: 2.4
Name: videodb-director-mcp
Version: 0.1.7
Summary: VideoDB MCP Server
Requires-Python: >=3.12
Requires-Dist: mcp[cli]>=1.3.0
Requires-Dist: python-socketio>=5.12.1
Requires-Dist: requests>=2.32.3
Requires-Dist: websocket-client>=1.8.0
